MANIFEST.in
README.rst
setup.cfg
setup.py
medialog/.DS_Store
medialog/__init__.py
medialog.issuu.egg-info/PKG-INFO
medialog.issuu.egg-info/SOURCES.txt
medialog.issuu.egg-info/dependency_links.txt
medialog.issuu.egg-info/entry_points.txt
medialog.issuu.egg-info/namespace_packages.txt
medialog.issuu.egg-info/not-zip-safe
medialog.issuu.egg-info/paster_plugins.txt
medialog.issuu.egg-info/requires.txt
medialog.issuu.egg-info/top_level.txt
medialog/issuu/.DS_Store
medialog/issuu/README.txt
medialog/issuu/__init__.py
medialog/issuu/configure.zcml
medialog/issuu/configure.zcml kopi
medialog/issuu/interfaces.py
medialog/issuu/settings.py
medialog/issuu/browser/__init__.py
medialog/issuu/browser/configure.zcml
medialog/issuu/browser/forms.py
medialog/issuu/browser/issuufullscreen.pt
medialog/issuu/browser/issuuimageview.pt
medialog/issuu/browser/issuuview.pt
medialog/issuu/browser/utils.py
medialog/issuu/browser/views.py
medialog/issuu/browser/themes/basicBlue-theme/crossdomain.xml
medialog/issuu/browser/themes/basicBlue-theme/issuu/basicBlue/crossdomain.xml
medialog/issuu/browser/themes/basicBlue-theme/issuu/basicBlue/layout.xml
medialog/issuu/browser/themes/basicBlue-theme/issuu/basicBlue/skins.fla
medialog/issuu/browser/themes/basicBlue-theme/issuu/basicBlue/skins.swf
medialog/issuu/browser/themes/basicGrey-theme/crossdomain.xml
medialog/issuu/browser/themes/basicGrey-theme/issuu/basicGrey/crossdomain.xml
medialog/issuu/browser/themes/basicGrey-theme/issuu/basicGrey/layout.xml
medialog/issuu/browser/themes/basicGrey-theme/issuu/basicGrey/skins.fla
medialog/issuu/browser/themes/basicGrey-theme/issuu/basicGrey/skins.swf
medialog/issuu/browser/themes/crayon-theme/crossdomain.xml
medialog/issuu/browser/themes/crayon-theme/issuu/crayon/crossdomain.xml
medialog/issuu/browser/themes/crayon-theme/issuu/crayon/layout.xml
medialog/issuu/browser/themes/crayon-theme/issuu/crayon/skins.fla
medialog/issuu/browser/themes/crayon-theme/issuu/crayon/skins.swf
medialog/issuu/browser/themes/white-theme/crossdomain.xml
medialog/issuu/browser/themes/white-theme/issuu/white/crossdomain.xml
medialog/issuu/browser/themes/white-theme/issuu/white/layout.xml
medialog/issuu/browser/themes/white-theme/issuu/white/skins.fla
medialog/issuu/browser/themes/white-theme/issuu/white/skins.swf
medialog/issuu/browser/themes/whiteMenu-theme/crossdomain.xml
