Metadata-Version: 1.1
Name: medialog.issuu
Version: 0.4
Summary: The goal is to integrate issuu.com's API with plone
Home-page: https://github.com/espenmn/medialog.issuu
Author: Espen Moe-Nilssen
Author-email: espen@medialog.no
License: GPL
Keywords: pdf viewer issuu.com plone
Platform: UNKNOWN
Classifier: Framework :: Plone
Classifier: Intended Audience :: Developers
Classifier: License :: OSI Approved :: GNU General Public License (GPL)
